pydrght/__init__.py
pydrght/bfa.py
pydrght/czi.py
pydrght/dchar.py
pydrght/di.py
pydrght/dist.py
pydrght/msdi.py
pydrght/pds.py
pydrght/pni.py
pydrght/rai.py
pydrght/rdi.py
pydrght/si.py
pydrght/tsdi.py
pydrght/copulas/__init__.py
pydrght/copulas/archimedean.py
pydrght/copulas/base.py
pydrght/copulas/elliptical.py
pydrght/copulas/extreme.py
pydrght/copulas/utils.py
pydrght/indices/__init__.py
pydrght/indices/sgi.py
pydrght/indices/spei.py
pydrght/indices/spi.py
pydrght/indices/ssfi.py
pydrght/indices/ssmi.py
pydrght/methods/__init__.py
pydrght/methods/cdf_estimators.py
pydrght/methods/param_estimator_pwm.py
pydrght/methods/param_estimators.py
pydrght/methods/ub_pwm.py
pydrght/pet/__init__.py
pydrght/pet/hargreaves.py
pydrght/pet/thornthwaite.py
pydrght/pet/utils.py
pydrght/utils/__init__.py
pydrght/utils/utils.py
pydrght-0.2.1.dist-info/licenses/LICENSE
pydrght-0.2.1.dist-info/METADATA
pydrght-0.2.1.dist-info/WHEEL
pydrght-0.2.1.dist-info/top_level.txt
pydrght-0.2.1.dist-info/RECORD
