Metadata-Version: 2.4
Name: pydrght
Version: 0.2.1
Summary: A comprehensive Python package for drought analysis, with standardized indices (SPI, SPEI, SSFI) and copula-based bivariate MSDI for multivariate drought characterization.
Author-email: Tolga Barış Terzi <tolgabaristerzi@ktu.edu.tr>
License-Expression: MIT
Project-URL: Homepage, https://github.com/terzitb/pydrght
Project-URL: Repository, https://github.com/terzitb/pydrght
Keywords: drought,SPI,SPEI,MSDI,indices,copulas,hydrology
Classifier: Intended Audience :: Science/Research
Classifier: Programming Language :: Python :: 3
Classifier: Operating System :: OS Independent
Classifier: Topic :: Scientific/Engineering :: Hydrology
Requires-Python: >=3.8
License-File: LICENSE
Requires-Dist: numpy>=1.23
Requires-Dist: pandas>=1.5
Requires-Dist: scipy>=1.10
Provides-Extra: excel
Requires-Dist: openpyxl>=3.0; extra == "excel"
Provides-Extra: dev
Requires-Dist: pytest>=7.0; extra == "dev"
Requires-Dist: pytest-cov>=4.0; extra == "dev"
Requires-Dist: jupyter>=1.0; extra == "dev"
Requires-Dist: nbconvert>=7.0; extra == "dev"
Dynamic: license-file
